{"stats": {"errors": 0, "failures": 0, "passes": 7, "skipped": 0, "encoding": "UTF-8", "total": 7}, "results": [{"classname": "index_test:TestDistance", "name": "test_avenue_distance", "time": 0.28823184967041016, "type": "success"}, {"classname": "index_test:TestDistance", "name": "test_distance", "time": 0.000209808349609375, "type": "success"}, {"classname": "index_test:TestDistance", "name": "test_distance_all", "time": 0.0010075569152832031, "type": "success"}, {"classname": "index_test:TestDistance", "name": "test_distance_between_neighbors_squared", "time": 0.43392038345336914, "type": "success"}, {"classname": "index_test:TestDistance", "name": "test_distance_with_neighbor", "time": 0.00025653839111328125, "type": "success"}, {"classname": "index_test:TestDistance", "name": "test_nearest_neighbors", "time": 0.0003609657287597656, "type": "success"}, {"classname": "index_test:TestDistance", "name": "test_street_distance", "time": 0.0001995563507080078, "type": "success"}]}